<annotation>
	<folder>originales</folder>
	<filename>00000322_hippo.jpg</filename>
	<path>/media/joseluis/razek_320GB/datasets/dataset_hipopotamo/originales/00000322.jpg</path>
	<source>
		<database>Unknown</database>
	</source>
	<size>
		<width>800</width>
		<height>506</height>
		<depth>3</depth>
	</size>
	<segmented>0</segmented>
	<object>
		<name>hipopotamo</name>
		<pose>Unspecified</pose>
		<truncated>0</truncated>
		<difficult>0</difficult>
		<bndbox>
			<xmin>332</xmin>
			<ymin>48</ymin>
			<xmax>715</xmax>
			<ymax>475</ymax>
		</bndbox>
	</object>
	<object>
		<name>hipopotamo</name>
		<pose>Unspecified</pose>
		<truncated>1</truncated>
		<difficult>0</difficult>
		<bndbox>
			<xmin>0</xmin>
			<ymin>170</ymin>
			<xmax>350</xmax>
			<ymax>497</ymax>
		</bndbox>
	</object>
</annotation>
