<annotation>
	<folder>dataset_hipopotamo</folder>
	<filename>00000382_hippo.jpg</filename>
	<path>/home/joseluis/Imágenes/dataset_hipopotamo/00000382.JPG</path>
	<source>
		<database>Unknown</database>
	</source>
	<size>
		<width>800</width>
		<height>533</height>
		<depth>3</depth>
	</size>
	<segmented>0</segmented>
	<object>
		<name>hipopotamo</name>
		<pose>Unspecified</pose>
		<truncated>0</truncated>
		<difficult>0</difficult>
		<bndbox>
			<xmin>108</xmin>
			<ymin>48</ymin>
			<xmax>389</xmax>
			<ymax>339</ymax>
		</bndbox>
	</object>
	<object>
		<name>hipopotamo</name>
		<pose>Unspecified</pose>
		<truncated>0</truncated>
		<difficult>0</difficult>
		<bndbox>
			<xmin>411</xmin>
			<ymin>180</ymin>
			<xmax>535</xmax>
			<ymax>334</ymax>
		</bndbox>
	</object>
	<object>
		<name>hipopotamo</name>
		<pose>Unspecified</pose>
		<truncated>0</truncated>
		<difficult>0</difficult>
		<bndbox>
			<xmin>561</xmin>
			<ymin>86</ymin>
			<xmax>749</xmax>
			<ymax>303</ymax>
		</bndbox>
	</object>
</annotation>
